{
  "translations" : {
    "EN" : {
      "name" : "Segment 2",
      "category" : "Customers"
    },
    "FR" : {
      "name" : "Segment 2",
      "category" : "Clients"
    }
  },
  "name" : "Segment 2",
  "category" : "Clients",
  "properties" : {
    "width" : 200.0
  },
  "requires" : "graph.retail;auth.scheme.CUS | auth.scheme.BSK_LINE | auth.scheme.BSK | _SYS_",
  "sql" : "{{CUS}}.`Segment2`",
  "path" : "retail.CUS.Segment2",
  "type" : "TEXT",
  "graph" : "retail",
  "refers_to_table" : true,
  "company" : "retail_demo"
}